README.md
setup.py
awsso/__init__.py
awsso/awsso.py
awsso/jira_approval.py
awsso.egg-info/PKG-INFO
awsso.egg-info/SOURCES.txt
awsso.egg-info/dependency_links.txt
awsso.egg-info/entry_points.txt
awsso.egg-info/requires.txt
awsso.egg-info/top_level.txt