Metadata-Version: 2.1
Name: awsso
Version: 0.6.0
Summary: aws command line tool
Home-page: https://github.com/Hireteammate/tools.git
Author: linhan
Author-email: lynnpen@gmail.com
Classifier: Programming Language :: Python :: 3
Classifier: Programming Language :: Python :: 3.8
Classifier: License :: OSI Approved :: MIT License
Classifier: Operating System :: OS Independent
